dockerdb/__init__.py
dockerdb/constants.py
dockerdb/piccolo_app.py
dockerdb/repository.py
dockerdb/commands/__init__.py
dockerdb/commands/create.py
dockerdb/commands/destroy.py
dockerdb/commands/start.py
dockerdb/commands/stop.py
dockerdb/migrations/__init__.py
piccolo_docker-0.1.0.dist-info/LICENSE
piccolo_docker-0.1.0.dist-info/METADATA
piccolo_docker-0.1.0.dist-info/WHEEL
piccolo_docker-0.1.0.dist-info/entry_points.txt
piccolo_docker-0.1.0.dist-info/top_level.txt
piccolo_docker-0.1.0.dist-info/RECORD
