Metadata-Version: 2.1
Name: piccolo-docker
Version: 0.1.0
Summary: Easily spin up databases for your Piccolo project using Docker
Home-page: https://github.com/piccolo-orm/piccolo_docker
Author: Antonio One
Author-email: antonio.one@pm.me
License: MIT
Platform: UNKNOWN
Classifier: License :: OSI Approved :: MIT License
Classifier: Programming Language :: Python
Classifier: Programming Language :: Python :: 3
Classifier: Programming Language :: Python :: 3.8
Classifier: Programming Language :: Python :: 3.9
Classifier: Programming Language :: Python :: Implementation :: CPython
Classifier: Framework :: AsyncIO
Classifier: Typing :: Typed
Classifier: Topic :: Database
Requires-Python: >=3.8.0
License-File: LICENSE
Requires-Dist: requirements.txt
